pyobs_gemini/__init__.py
pyobs_gemini/api.py
pyobs_gemini/gemini.py
pyobs_gemini/geminidriver.py
pyobs_gemini-0.1.0.dist-info/LICENSE
pyobs_gemini-0.1.0.dist-info/WHEEL
pyobs_gemini-0.1.0.dist-info/METADATA
pyobs_gemini-0.1.0.dist-info/RECORD
