Metadata-Version: 2.1
Name: pyobs-gemini
Version: 0.1.0
Summary: pyobs module for Optec Gemini focusser/rotator
License: MIT
Author: Tim-Oliver Husser
Author-email: thusser@uni-goettingen.de
Requires-Python: >=3.9,<3.11
Classifier: License :: OSI Approved :: MIT License
Classifier: Programming Language :: Python :: 3
Classifier: Programming Language :: Python :: 3.10
Classifier: Programming Language :: Python :: 3.9
Requires-Dist: aioserial (>=1.3.1,<2.0.0)
Requires-Dist: astropy (>=5.1,<6.0)
